protos/authentication_pb2.py
protos/authentication_pb2_grpc.py
protos/authentication_type_pb2.py
protos/authentication_type_pb2_grpc.py
protos/client_info_pb2.py
protos/client_info_pb2_grpc.py
protos/error_pb2.py
protos/error_pb2_grpc.py
protos/queryhandler_pb2.py
protos/queryhandler_pb2_grpc.py
pysqream_blue/__init__.py
pysqream_blue/array_parser.py
pysqream_blue/casting.py
pysqream_blue/connection.py
pysqream_blue/cursor.py
pysqream_blue/globals.py
pysqream_blue/logger.py
pysqream_blue/pysqream_blue.py
pysqream_blue/utils.py
pysqream_blue-1.0.48.dist-info/LICENSE
pysqream_blue-1.0.48.dist-info/METADATA
pysqream_blue-1.0.48.dist-info/WHEEL
pysqream_blue-1.0.48.dist-info/top_level.txt
pysqream_blue-1.0.48.dist-info/RECORD
