Metadata-Version: 2.1
Name: pysqream-blue
Version: 1.0.48
Summary: DB-API connector for SQream DB
Home-page: https://github.com/SQream/pysqream-blue
Author: SQream
Author-email: info@sqream.com
Keywords: database db-api sqream sqreamdbV2
Classifier: Programming Language :: Python :: 3.9
Classifier: License :: OSI Approved :: BSD License
Classifier: Operating System :: OS Independent
Requires-Python: >=3.9
Requires-Dist: google==3.0.0
Requires-Dist: googleapis-common-protos==1.53.0
Requires-Dist: setuptools==65.5.1
Requires-Dist: grpcio==1.53.0
Requires-Dist: grpcio-tools==1.47.0
Requires-Dist: numpy>=1.20
Requires-Dist: python-dotenv>=1.0.0
